json_hyperscan/__init__.py
json_hyperscan/json_hyperscan.py
json_hyperscan-0.1.0.dist-info/METADATA
json_hyperscan-0.1.0.dist-info/WHEEL
json_hyperscan-0.1.0.dist-info/licenses/LICENSE.txt
json_hyperscan-0.1.0.dist-info/RECORD
