Metadata-Version: 2.4
Name: json-hyperscan
Version: 0.1.0
Summary: Library for matching large numbers of JSONPath expressions simultaniously
Project-URL: Homepath, https://github.com/captonsnake/json_hyperscan
Project-URL: Issues, https://github.com/captonsnake/json_hyperscan/issues
Author-email: Samual McCracken <mccracken.landon+pip@gmail.com>
License-Expression: MIT
License-File: LICENSE.txt
Classifier: Intended Audience :: Developers
Classifier: Operating System :: OS Independent
Classifier: Programming Language :: Python :: 3
Classifier: Topic :: File Formats :: JSON
Requires-Python: >=3.10
Requires-Dist: jsonpath-rfc9535>=0.1.6
